{
	"G": [
		"G",
		"Gmaj7",
		"G6",
		"Gadd9",
		"Gmaj9",
		"Gmaj13",
		"Gsus2",
		"Gsus4",
		"G6/9",
		"G7",
		"G9",
		"G11",
		"G13",
		"G7sus4",
		"Gaug",
		"Gm7",
		"Gm7b5",
		"Gm9",
		"Gm11",
		"Gm13"
	],
	"A": [
		"A",
		"Amaj7",
		"A6",
		"Aadd9",
		"Amaj9",
		"Amaj13",
		"Asus2",
		"Asus4",
		"A6/9",
		"A7",
		"A9",
		"A11",
		"A13",
		"A7sus4",
		"Aaug",
		"Am7",
		"Am7b5",
		"Am9",
		"Am11",
		"Am13"
	],
	"B": [
		"B",
		"Bmaj7",
		"B6",
		"Badd9",
		"Bmaj9",
		"Bmaj13",
		"Bsus2",
		"Bsus4",
		"B6/9",
		"B7",
		"B9",
		"B11",
		"B13",
		"B7sus4",
		"Baug",
		"Bm7",
		"Bm7b5",
		"Bm9",
		"Bm11",
		"Bm13"
	],
	"C": [
		"C",
		"Cmaj7",
		"C6",
		"Cadd9",
		"Cmaj9",
		"Cmaj13",
		"Csus2",
		"Csus4",
		"C6/9",
		"C7",
		"C9",
		"C11",
		"C13",
		"C7sus4",
		"Caug",
		"Cm7",
		"Cm7b5",
		"Cm9",
		"Cm11",
		"Cm13"
	],
	"D": [
		"D",
		"Dmaj7",
		"D6",
		"Dadd9",
		"Dmaj9",
		"Dmaj13",
		"Dsus2",
		"Dsus4",
		"D6/9",
		"D7",
		"D9",
		"D11",
		"D13",
		"D7sus4",
		"Daug",
		"Dm7",
		"Dm7b5",
		"Dm9",
		"Dm11",
		"Dm13"
	],
	"E": [
		"E",
		"Emaj7",
		"E6",
		"Eadd9",
		"Emaj9",
		"Emaj13",
		"Esus2",
		"Esus4",
		"E6/9",
		"E7",
		"E9",
		"E11",
		"E13",
		"E7sus4",
		"Eaug",
		"Em7",
		"Em7b5",
		"Em9",
		"Em11",
		"Em13"
	],
	"F#": [
		"F#",
		"F#maj7",
		"F#6",
		"F#add9",
		"F#maj9",
		"F#maj13",
		"F#sus2",
		"F#sus4",
		"F#6/9",
		"F#7",
		"F#9",
		"F#11",
		"F#13",
		"F#7sus4",
		"F#aug",
		"F#m7",
		"F#m7b5",
		"F#m9",
		"F#m11",
		"F#m13"
	]
}
